Mopidy_FileManager-0.2.0.dist-info/DESCRIPTION.rst
Mopidy_FileManager-0.2.0.dist-info/METADATA
Mopidy_FileManager-0.2.0.dist-info/RECORD
Mopidy_FileManager-0.2.0.dist-info/WHEEL
Mopidy_FileManager-0.2.0.dist-info/entry_points.txt
Mopidy_FileManager-0.2.0.dist-info/metadata.json
Mopidy_FileManager-0.2.0.dist-info/top_level.txt
mopidy_filemanager/__init__.py
mopidy_filemanager/ext.conf
mopidy_filemanager/file_manager.py
mopidy_filemanager/static/index.html
mopidy_filemanager/static/css/angular-filemanager.min.css
mopidy_filemanager/static/css/bootstrap.min.css
mopidy_filemanager/static/fonts/glyphicons-halflings-regular.eot
mopidy_filemanager/static/fonts/glyphicons-halflings-regular.svg
mopidy_filemanager/static/fonts/glyphicons-halflings-regular.ttf
mopidy_filemanager/static/fonts/glyphicons-halflings-regular.woff
mopidy_filemanager/static/fonts/glyphicons-halflings-regular.woff2
mopidy_filemanager/static/js/angular-filemanager.min.js
mopidy_filemanager/static/js/angular-translate.min.js
mopidy_filemanager/static/js/angular.min.js
mopidy_filemanager/static/js/bootstrap.min.js
mopidy_filemanager/static/js/jquery.min.js
mopidy_filemanager/static/js/ng-file-upload.min.js
